MANIFEST.in
licence.txt
readme.md
setup.py
pykeops/__init__.py
pykeops/config.py
pykeops/keops_version
pykeops/licence.txt
pykeops/readme.md
pykeops.egg-info/PKG-INFO
pykeops.egg-info/SOURCES.txt
pykeops.egg-info/dependency_links.txt
pykeops.egg-info/requires.txt
pykeops.egg-info/top_level.txt
pykeops/benchmarks/README.txt
pykeops/benchmarks/benchmark_KNN.py
pykeops/benchmarks/benchmark_utils.py
pykeops/benchmarks/dataset_utils.py
pykeops/benchmarks/plot_accuracy.py
pykeops/benchmarks/plot_benchmark_convolutions.py
pykeops/benchmarks/plot_benchmark_grad1convolutions.py
pykeops/benchmarks/plot_benchmark_high_dimension.py
pykeops/benchmarks/plot_benchmark_invkernel.py
pykeops/benchmarks/plot_benchmarks_convolutions_3D.py
pykeops/common/__init__.py
pykeops/common/get_options.py
pykeops/common/gpu_utils.py
pykeops/common/lazy_tensor.py
pykeops/common/operations.py
pykeops/common/parse_type.py
pykeops/common/utils.py
pykeops/common/keops_io/LoadKeOps.py
pykeops/common/keops_io/LoadKeOps_cpp.py
pykeops/common/keops_io/LoadKeOps_nvrtc.py
pykeops/common/keops_io/__init__.py
pykeops/common/keops_io/pykeops_nvrtc.cpp
pykeops/examples/README.txt
pykeops/examples/__init__.py
pykeops/examples/numpy/README.txt
pykeops/examples/numpy/plot_generic_syntax_numpy.py
pykeops/examples/numpy/plot_gpu_select_numpy.py
pykeops/examples/numpy/plot_grid_cluster_numpy.py
pykeops/examples/numpy/plot_test_ArgKMin.py
pykeops/examples/numpy/plot_test_invkernel_numpy.py
pykeops/examples/numpy/plot_test_invkernel_numpy_helper.py
pykeops/examples/numpy/plot_test_softmax_numpy.py
pykeops/examples/numpy/plot_test_softmax_numpy_helper.py
pykeops/examples/pytorch/README.txt
pykeops/examples/pytorch/plot_advanced_formula.py
pykeops/examples/pytorch/plot_anisotropic_kernels.py
pykeops/examples/pytorch/plot_generic_syntax_pytorch.py
pykeops/examples/pytorch/plot_generic_syntax_pytorch_LSE.py
pykeops/examples/pytorch/plot_generic_syntax_pytorch_LSE_vect.py
pykeops/examples/pytorch/plot_gpu_select_example.py
pykeops/examples/pytorch/plot_grid_cluster_pytorch.py
pykeops/examples/pytorch/plot_multi_gpu.py
pykeops/examples/pytorch/plot_test_invkernel_torch.py
