Metadata-Version: 2.4
Name: pykeops
Version: 2.3
Summary: Python bindings of KeOps: KErnel OPerationS, on CPUs and GPUs, with autodiff and without memory overflows
Home-page: http://www.kernel-operations.io/
Author: B. Charlier, J. Feydy, J. Glaunes
Author-email: benjamin.charlier@umontpellier.fr, jean.feydy@gmail.com, alexis.glaunes@parisdescartes.fr
Project-URL: Bug Reports, https://github.com/getkeops/keops/issues
Project-URL: Source, https://github.com/getkeops/keops
Keywords: kernels gpu autodiff
Classifier: Development Status :: 5 - Production/Stable
Classifier: Intended Audience :: Developers
Classifier: Topic :: Scientific/Engineering
Classifier: License :: OSI Approved :: MIT License
Classifier: Operating System :: POSIX :: Linux
Classifier: Operating System :: MacOS :: MacOS X
Classifier: Programming Language :: C++
Classifier: Programming Language :: Python :: 3 :: Only
Requires-Python: >=3.8
Requires-Dist: numpy
Requires-Dist: pybind11
Requires-Dist: keopscore==2.3
Provides-Extra: full
Requires-Dist: sphinx; extra == "full"
Requires-Dist: sphinx-gallery; extra == "full"
Requires-Dist: recommonmark; extra == "full"
Requires-Dist: sphinxcontrib-httpdomain; extra == "full"
Requires-Dist: sphinx_rtd_theme; extra == "full"
Requires-Dist: sphinx-prompt; extra == "full"
Requires-Dist: breathe; extra == "full"
Requires-Dist: matplotlib; extra == "full"
Requires-Dist: imageio; extra == "full"
Requires-Dist: torch; extra == "full"
Requires-Dist: gpytorch; extra == "full"
Requires-Dist: scikit-learn; extra == "full"
Requires-Dist: multiprocess; extra == "full"
Requires-Dist: faiss; extra == "full"
Requires-Dist: h5py; extra == "full"
Requires-Dist: jaxlib; extra == "full"
Requires-Dist: jax; extra == "full"
Provides-Extra: test
Requires-Dist: pytest; extra == "test"
Requires-Dist: numpy; extra == "test"
Requires-Dist: torch; extra == "test"
Dynamic: author
Dynamic: author-email
Dynamic: classifier
Dynamic: description
Dynamic: description-content-type
Dynamic: home-page
Dynamic: keywords
Dynamic: project-url
Dynamic: provides-extra
Dynamic: requires-dist
Dynamic: requires-python
Dynamic: summary
